iris_agent/__init__.py
iris_agent/agent.py
iris_agent/async_agent.py
iris_agent/llm.py
iris_agent/messages.py
iris_agent/prompts.py
iris_agent/py.typed
iris_agent/tools.py
iris_agent/types.py
iris_agent-0.1.3.dist-info/licenses/LICENSE
iris_agent-0.1.3.dist-info/METADATA
iris_agent-0.1.3.dist-info/WHEEL
iris_agent-0.1.3.dist-info/top_level.txt
iris_agent-0.1.3.dist-info/RECORD
