Metadata-Version: 2.4
Name: iris-agent
Version: 0.1.3
Summary: A lightweight Python AI agent framework for building autonomous agents.
Author-email: Abhishek Gehlot <abhigehlot123@gmail.com>
License: MIT
Project-URL: Homepage, https://github.com/mrgehlot/iris-agent
Project-URL: Documentation, https://github.com/mrgehlot/iris-agent#readme
Project-URL: Repository, https://github.com/mrgehlot/iris-agent
Project-URL: Issues, https://github.com/mrgehlot/iris-agent/issues
Keywords: ai,agent,llm,openai,framework,tools,prompts
Classifier: Development Status :: 3 - Alpha
Classifier: Intended Audience :: Developers
Classifier: License :: OSI Approved :: MIT License
Classifier: Programming Language :: Python :: 3
Classifier: Programming Language :: Python :: 3.10
Classifier: Programming Language :: Python :: 3.11
Classifier: Programming Language :: Python :: 3.12
Classifier: Topic :: Software Development :: Libraries :: Python Modules
Classifier: Topic :: Scientific/Engineering :: Artificial Intelligence
Requires-Python: >=3.10
License-File: LICENSE
Requires-Dist: openai>=1.0.0
Requires-Dist: rich>=13.0.0
Provides-Extra: dev
Requires-Dist: pytest>=7.0.0; extra == "dev"
Requires-Dist: pytest-asyncio>=0.21.0; extra == "dev"
Requires-Dist: pytest-cov>=4.0.0; extra == "dev"
Requires-Dist: black>=23.0.0; extra == "dev"
Requires-Dist: isort>=5.12.0; extra == "dev"
Requires-Dist: mkdocs>=1.5.0; extra == "dev"
Requires-Dist: mkdocs-material>=9.7.1; extra == "dev"
Dynamic: license-file
